Workbook
Name Slicer_Country: #N/A
Name Slicer_Earners: #N/A
Name Slicer_Risk_Flag: #N/A

Sheet Summery sheet
B2: GLOBAL HOUSEHOLD FiNANCIAL DYNAMICS ││SUMMARY DASHBOARD
B3: ││(Analysis of 4,985 Households across 5 Countries | Data Analyst Project)││
B5: 1. KEY PERFORMANCE INDICATORS
B6: 4985 Total Household | D6: 5 Countries Analysed | F6: =TEXT(AVERAGE('STEP-2 CLEANED_DATA_ FROM_POWER'!G2:G4986),"#,##0.00")&CHAR(10)&" Avg Monthly Income" -> 4,945.92 Avg Monthly Income
B10: =TEXT(AVERAGE('STEP-2 CLEANED_DATA_ FROM_POWER'!J2:J4986),"#,##0.00") & CHAR(10)& " Avg Monthly Savings" -> 1,396.33 Avg Monthly Savings | D10: =TEXT(AVERAGE('STEP-2 CLEANED_DATA_ FROM_POWER'!L2:L4986)*100,"0.00")&"%"&CHAR(10)&"Avg Savings Rate" -> 32.18% Avg Savings Rate | F10: =TEXT(COUNTIF('STEP-2 CLEANED_DATA_ FROM_POWER'!N2:N4986,"High Risk")/4985*100,"0.00")&"%"&CHAR(10)&"Households at High Risk" -> 19.38% Households at High Risk
B14: 2. COUNTRY-WISE COMPARISON
B15: Country | C15: Household | D15: AVG Income | E15: AVG Savings | F15: Savings Rate | G15: Expense Ratio | H15: High Risk
B16: Brazil | C16: =COUNTIF('STEP-2 CLEANED_DATA_ FROM_POWER'!B:B,"Brazil") -> 738 | D16: =AVERAGEIF('STEP-2 CLEANED_DATA_ FROM_POWER'!B:B,"Brazil",'STEP-2 CLEANED_DATA_ FROM_POWER'!G:G) -> 2649.0738 | E16: =AVERAGEIF('STEP-2 CLEANED_DATA_ FROM_POWER'!B:B,"Brazil",'STEP-2 CLEANED_DATA_ FROM_POWER'!J:J) -> 1093.9416 | F16: =AVERAGEIF('STEP-2 CLEANED_DATA_ FROM_POWER'!B:B,"Brazil",'STEP-2 CLEANED_DATA_ FROM_POWER'!L:L) -> 0.39788995 | G16: =AVERAGEIF('STEP-2 CLEANED_DATA_ FROM_POWER'!B:B,"Brazil",'STEP-2 CLEANED_DATA_ FROM_POWER'!M:M) -> 0.60211204 | H16: ='Advance Analysis'!B2 -> 102
B17: Germany | C17: =COUNTIF('STEP-2 CLEANED_DATA_ FROM_POWER'!B:B,"Germany") -> 1028 | D17: =AVERAGEIF('STEP-2 CLEANED_DATA_ FROM_POWER'!B:B,"Germany",'STEP-2 CLEANED_DATA_ FROM_POWER'!G:G) -> 7172.6152 | E17: =AVERAGEIF('STEP-2 CLEANED_DATA_ FROM_POWER'!B:B,"Germany",'STEP-2 CLEANED_DATA_ FROM_POWER'!J:J) -> 1180.5755 | F17: =AVERAGEIF('STEP-2 CLEANED_DATA_ FROM_POWER'!B:B,"Germany",'STEP-2 CLEANED_DATA_ FROM_POWER'!L:L) -> 0.158798 | G17: =AVERAGEIF('STEP-2 CLEANED_DATA_ FROM_POWER'!B:B,"Germany",'STEP-2 CLEANED_DATA_ FROM_POWER'!M:M) -> 0.84120205 | H17: ='Advance Analysis'!B3 -> 313
B18: India | C18: =COUNTIF('STEP-2 CLEANED_DATA_ FROM_POWER'!B:B,"India") -> 1212 | D18: =AVERAGEIF('STEP-2 CLEANED_DATA_ FROM_POWER'!B:B,"India",'STEP-2 CLEANED_DATA_ FROM_POWER'!G:G) -> 1345.4775 | E18: =AVERAGEIF('STEP-2 CLEANED_DATA_ FROM_POWER'!B:B,"India",'STEP-2 CLEANED_DATA_ FROM_POWER'!J:J) -> 623.68461 | F18: =AVERAGEIF('STEP-2 CLEANED_DATA_ FROM_POWER'!B:B,"India",'STEP-2 CLEANED_DATA_ FROM_POWER'!L:L) -> 0.42077342 | G18: =AVERAGEIF('STEP-2 CLEANED_DATA_ FROM_POWER'!B:B,"India",'STEP-2 CLEANED_DATA_ FROM_POWER'!M:M) -> 0.57922586 | H18: ='Advance Analysis'!B4 -> 170
B19: UK | C19: =COUNTIF('STEP-2 CLEANED_DATA_ FROM_POWER'!B:B,"UK") -> 727 | D19: =AVERAGEIF('STEP-2 CLEANED_DATA_ FROM_POWER'!B:B,"UK",'STEP-2 CLEANED_DATA_ FROM_POWER'!G:G) -> 7073.7997 | E19: =AVERAGEIF('STEP-2 CLEANED_DATA_ FROM_POWER'!B:B,"UK",'STEP-2 CLEANED_DATA_ FROM_POWER'!J:J) -> 2040.8497 | F19: =AVERAGEIF('STEP-2 CLEANED_DATA_ FROM_POWER'!B:B,"UK",'STEP-2 CLEANED_DATA_ FROM_POWER'!L:L) -> 0.30718717 | G19: =AVERAGEIF('STEP-2 CLEANED_DATA_ FROM_POWER'!B:B,"UK",'STEP-2 CLEANED_DATA_ FROM_POWER'!M:M) -> 0.69281287 | H19: ='Advance Analysis'!B5 -> 148
B20: USA | C20: =COUNTIF('STEP-2 CLEANED_DATA_ FROM_POWER'!B:B,"USA") -> 1280 | D20: =AVERAGEIF('STEP-2 CLEANED_DATA_ FROM_POWER'!B:B,"USA",'STEP-2 CLEANED_DATA_ FROM_POWER'!G:G) -> 6682.4927 | E20: =AVERAGEIF('STEP-2 CLEANED_DATA_ FROM_POWER'!B:B,"USA",'STEP-2 CLEANED_DATA_ FROM_POWER'!J:J) -> 2109.4961 | F20: =AVERAGEIF('STEP-2 CLEANED_DATA_ FROM_POWER'!B:B,"USA",'STEP-2 CLEANED_DATA_ FROM_POWER'!L:L) -> 0.32336205 | G20: =AVERAGEIF('STEP-2 CLEANED_DATA_ FROM_POWER'!B:B,"USA",'STEP-2 CLEANED_DATA_ FROM_POWER'!M:M) -> 0.67663796 | H20: ='Advance Analysis'!B6 -> 233
B22: 3.RISK PROFILE & PERFORMANCE FLAGS
B23: Risk Classification | E23: Performance vs Country Average
B24: ✅ Safe | C24: 3754 | D24: 75.31% | E24: ⭐ Outperformer | F24: =COUNTIF('STEP-2 CLEANED_DATA_ FROM_POWER'!R:R,"Outperformer") -> 1514 | G24: 30.37%
B25: ⚠️ Medium Risk | C25: 265 | D25: 5.32% | E25: ➖ Normal | F25: =COUNTIF('STEP-2 CLEANED_DATA_ FROM_POWER'!R:R,"Normal") -> 2220 | G25: 44.53%
B26: 🔴 High Risk | C26: 966 | D26: 19.38% | E26: 📉 Underperformer | F26: =COUNTIF('STEP-2 CLEANED_DATA_ FROM_POWER'!R:R,"Underperformer") -> 1251 | G26: 25.09%
B29: 4.EARNER EFFECT AND FAMILY SIZE IMPACT
B30: Earner Effect on Savings | F30: Scenario: Expense Reduction Impact
B31: Earner | C31: Household | D31: AVG savings | E31: Savings rate | F31: Expense cut | G31: House hold turning safe | H31: Cumulative %
B32: 1 | C32: =COUNTIF('STEP-2 CLEANED_DATA_ FROM_POWER'!E:E,1) -> 1685 | D32: =AVERAGEIF('STEP-2 CLEANED_DATA_ FROM_POWER'!E:E,1,'STEP-2 CLEANED_DATA_ FROM_POWER'!J:J) -> 631.57833 | E32: =AVERAGEIF('STEP-2 CLEANED_DATA_ FROM_POWER'!E:E,1,'STEP-2 CLEANED_DATA_ FROM_POWER'!L:L) -> 0.23887597 | F32: 0.05 | G32: 98 | H32: 0.102
B33: 2 | C33: =COUNTIF('STEP-2 CLEANED_DATA_ FROM_POWER'!E:E,2) -> 1100 | D33: =AVERAGEIF('STEP-2 CLEANED_DATA_ FROM_POWER'!E:E,2,'STEP-2 CLEANED_DATA_ FROM_POWER'!J:J) -> 1505.3251 | E33: =AVERAGEIF('STEP-2 CLEANED_DATA_ FROM_POWER'!E:E,2,'STEP-2 CLEANED_DATA_ FROM_POWER'!L:L) -> 0.3601618 | F33: 0.1 | G33: 320 | H33: 0.331
B34: 3 | C34: =COUNTIF('STEP-2 CLEANED_DATA_ FROM_POWER'!E:E,3) -> 2200 | D34: =AVERAGEIF('STEP-2 CLEANED_DATA_ FROM_POWER'!E:E,3,'STEP-2 CLEANED_DATA_ FROM_POWER'!J:J) -> 1927.5691 | E34: =AVERAGEIF('STEP-2 CLEANED_DATA_ FROM_POWER'!E:E,3,'STEP-2 CLEANED_DATA_ FROM_POWER'!L:L) -> 0.36609501 | F34: 0.15 | G34: 498 | H34: 0.516
F35: 0.2 | G35: 700 | H35: 0.721
B38: 5.FAMILY SIZE → SAVINGS RATE TREND
B39: Family Size | C39: Average savings | D39: Savings rate | E39: High risk of House hold
B40: 1 | C40: =AVERAGEIF('STEP-2 CLEANED_DATA_ FROM_POWER'!D:D,1,'STEP-2 CLEANED_DATA_ FROM_POWER'!J:J) -> 1150.314 | D40: =AVERAGEIF('STEP-2 CLEANED_DATA_ FROM_POWER'!D:D,1,'STEP-2 CLEANED_DATA_ FROM_POWER'!L:L) -> 0.45931243 | E40: =COUNTIFS('STEP-2 CLEANED_DATA_ FROM_POWER'!D:D,1,'STEP-2 CLEANED_DATA_ FROM_POWER'!N:N,"High Risk") -> 40
B41: 2 | C41: =AVERAGEIF('STEP-2 CLEANED_DATA_ FROM_POWER'!D:D,2,'STEP-2 CLEANED_DATA_ FROM_POWER'!J:J) -> 1499.2859 | D41: =AVERAGEIF('STEP-2 CLEANED_DATA_ FROM_POWER'!D:D,2,'STEP-2 CLEANED_DATA_ FROM_POWER'!L:L) -> 0.41667947 | E41: =COUNTIFS('STEP-2 CLEANED_DATA_ FROM_POWER'!D:D,2,'STEP-2 CLEANED_DATA_ FROM_POWER'!N:N,"High Risk") -> 76
B42: 3 | C42: =AVERAGEIF('STEP-2 CLEANED_DATA_ FROM_POWER'!D:D,3,'STEP-2 CLEANED_DATA_ FROM_POWER'!J:J) -> 1741.8436 | D42: =AVERAGEIF('STEP-2 CLEANED_DATA_ FROM_POWER'!D:D,3,'STEP-2 CLEANED_DATA_ FROM_POWER'!L:L) -> 0.40819857 | E42: =COUNTIFS('STEP-2 CLEANED_DATA_ FROM_POWER'!D:D,3,'STEP-2 CLEANED_DATA_ FROM_POWER'!N:N,"High Risk") -> 77
B43: 4 | C43: =AVERAGEIF('STEP-2 CLEANED_DATA_ FROM_POWER'!D:D,4,'STEP-2 CLEANED_DATA_ FROM_POWER'!J:J) -> 1533.9912 | D43: =AVERAGEIF('STEP-2 CLEANED_DATA_ FROM_POWER'!D:D,4,'STEP-2 CLEANED_DATA_ FROM_POWER'!L:L) -> 0.32861033 | E43: =COUNTIFS('STEP-2 CLEANED_DATA_ FROM_POWER'!D:D,4,'STEP-2 CLEANED_DATA_ FROM_POWER'!N:N,"High Risk") -> 123
B44: 5 | C44: =AVERAGEIF('STEP-2 CLEANED_DATA_ FROM_POWER'!D:D,5,'STEP-2 CLEANED_DATA_ FROM_POWER'!J:J) -> 1610.3058 | D44: =AVERAGEIF('STEP-2 CLEANED_DATA_ FROM_POWER'!D:D,5,'STEP-2 CLEANED_DATA_ FROM_POWER'!L:L) -> 0.29905427 | E44: =COUNTIFS('STEP-2 CLEANED_DATA_ FROM_POWER'!D:D,5,'STEP-2 CLEANED_DATA_ FROM_POWER'!N:N,"High Risk") -> 141
B45: 6 | C45: =AVERAGEIF('STEP-2 CLEANED_DATA_ FROM_POWER'!D:D,6,'STEP-2 CLEANED_DATA_ FROM_POWER'!J:J) -> 1409.4629 | D45: =AVERAGEIF('STEP-2 CLEANED_DATA_ FROM_POWER'!D:D,6,'STEP-2 CLEANED_DATA_ FROM_POWER'!L:L) -> 0.27051931 | E45: =COUNTIFS('STEP-2 CLEANED_DATA_ FROM_POWER'!D:D,6,'STEP-2 CLEANED_DATA_ FROM_POWER'!N:N,"High Risk") -> 138
B46: 7 | C46: =AVERAGEIF('STEP-2 CLEANED_DATA_ FROM_POWER'!D:D,7,'STEP-2 CLEANED_DATA_ FROM_POWER'!J:J) -> 1166.3825 | D46: =AVERAGEIF('STEP-2 CLEANED_DATA_ FROM_POWER'!D:D,7,'STEP-2 CLEANED_DATA_ FROM_POWER'!L:L) -> 0.21848387 | E46: =COUNTIFS('STEP-2 CLEANED_DATA_ FROM_POWER'!D:D,7,'STEP-2 CLEANED_DATA_ FROM_POWER'!N:N,"High Risk") -> 168
B47: 8 | C47: =AVERAGEIF('STEP-2 CLEANED_DATA_ FROM_POWER'!D:D,8,'STEP-2 CLEANED_DATA_ FROM_POWER'!J:J) -> 1067.2516 | D47: =AVERAGEIF('STEP-2 CLEANED_DATA_ FROM_POWER'!D:D,8,'STEP-2 CLEANED_DATA_ FROM_POWER'!L:L) -> 0.17218755 | E47: =COUNTIFS('STEP-2 CLEANED_DATA_ FROM_POWER'!D:D,8,'STEP-2 CLEANED_DATA_ FROM_POWER'!N:N,"High Risk") -> 203
B50: 6.KEY ANALYST INSIGHT
B52: India & Brazil lead savings rates (42% & 40%) despite the lowest absolute incomes — efficiency, not just earnings, drives financial health.
B53: Germany has the highest avg income (7,173) but the lowest savings rate (15.9%) — high cost of living erodes savings power.
B54: Every additional earner dramatically lifts savings — 1 earner saves 632/mo avg vs 3 earners saving 1,928/mo. That is a 205% jump
B55: Family size is a savings drag — a family of 8 saves 63% less than a family of 3 (17% vs 41% savings rate)
B56: A 20% expense reduction would turn 700 High Risk households into Safe — that is 72.5% of all High Risk households rescued

Sheet STEP-2 CLEANED_DATA_ FROM_POWER
A1: Household_ID | B1: Country | C1: City | D1: Family_Size | E1: Earners | F1: Primary_Income | G1: Total_Household_Income | H1: Estimated_Taxes | I1: Monthly_Expenses | J1: Monthly_Savings | K1: Net Income | L1: Savings Rate% | M1: Expense Ratio | N1: Risk_Flag | O1: Income Per Person | P1: Country_AVG_Rate | Q1: Vs country_Average | R1: Performance_flag | S1: Saving At 5% | T1: Saving at 10% | U1: Saving at 15% | V1: Saving at 20%
A2: 1 | B2: India | C2: Mumbai | D2: 5 | E2: 3 | F2: 1032.29 | G2: 2132.95 | H2: 213.3 | I2: 611.63 | J2: 1308.02 | K2: =Global_Household_Financial_Dyna[[#This Row],[Total_Household_Income]]-Global_Household_Financial_Dyna[[#This Row],[Estimated_Taxes]] -> 1919.65 | L2: =Global_Household_Financial_Dyna[[#This Row],[Monthly_Savings]]/Global_Household_Financial_Dyna[[#This Row],[Net Income]] -> 0.68138463 | M2: =Global_Household_Financial_Dyna[[#This Row],[Monthly_Expenses]]/Global_Household_Financial_Dyna[[#This Row],[Net Income]] -> 0.31861537 | N2: =IF(Global_Household_Financial_Dyna[[#This Row],[Monthly_Savings]]<0,"High Risk", IF(Global_Household_Financial_Dyna[[#This Row],[Savings Rate%]]<0.1, "Medium", "Safe")) -> Safe | O2: =Global_Household_Financial_Dyna[[#This Row],[Total_Household_Income]]/Global_Household_Financial_Dyna[[#This Row],[Family_Size]] -> 426.59 | P2: =AVERAGEIF($B$2:$B$4986,$B2,$L$2:$L$4986) -> 0.42077342 | Q2: =L2-P2 -> 0.26061121 | R2: =IF(Global_Household_Financial_Dyna[[#This Row],[Vs country_Average]]<-0.2, "Underperformer", IF(Global_Household_Financial_Dyna[[#This Row],[Vs country_Average]]>0.2, "Outperformer", "Normal")) -> Outperformer | S2: =IF(Global_Household_Financial_Dyna[[#This Row],[Risk_Flag]]="High Risk", Global_Household_Financial_Dyna[[#This Row],[Monthly_Savings]]+(Global_Household_Financial_Dyna[[#This Row],[Net Income]]*Global_Household_Financial_Dyna[[#This Row],[Expense Ratio]]*0.05),Global_Household_Financial_Dyna[[#This Row],[Monthly_Savings]]) -> 1308.02 | T2: =IF(Global_Household_Financial_Dyna[[#This Row],[Risk_Flag]]= "High Risk",Global_Household_Financial_Dyna[[#This Row],[Monthly_Savings]]+Global_Household_Financial_Dyna[[#This Row],[Net Income]]*(Global_Household_Financial_Dyna[[#This Row],[Expense Ratio]]*0.1),Global_Household_Financial_Dyna[[#This Row],[Monthly_Savings]]) -> 1308.02 | U2: =IF(Global_Household_Financial_Dyna[[#This Row],[Risk_Flag]]="High risk",Global_Household_Financial_Dyna[[#This Row],[Monthly_Savings]]+Global_Household_Financial_Dyna[[#This Row],[Net Income]]*(Global_Household_Financial_Dyna[[#This Row],[Expense Ratio]]*0.15),Global_Household_Financial_Dyna[[#This Row],[Monthly_Savings]]) -> 1308.02 | V2: =IF(Global_Household_Financial_Dyna[[#This Row],[Risk_Flag]]="High risk",Global_Household_Financial_Dyna[[#This Row],[Monthly_Savings]]+Global_Household_Financial_Dyna[[#This Row],[Net Income]]*(Global_Household_Financial_Dyna[[#This Row],[Expense Ratio]]*0.2),Global_Household_Financial_Dyna[[#This Row],[Monthly_Savings]]) -> 1308.02
A3: 2 | B3: UK | C3: London | D3: 2 | E3: 1 | F3: 5316.57 | G3: 5316.57 | H3: 1329.14 | I3: 2240.25 | J3: 1747.18 | K3: =Global_Household_Financial_Dyna[[#This Row],[Total_Household_Income]]-Global_Household_Financial_Dyna[[#This Row],[Estimated_Taxes]] -> 3987.43 | L3: =Global_Household_Financial_Dyna[[#This Row],[Monthly_Savings]]/Global_Household_Financial_Dyna[[#This Row],[Net Income]] -> 0.43817196 | M3: =Global_Household_Financial_Dyna[[#This Row],[Monthly_Expenses]]/Global_Household_Financial_Dyna[[#This Row],[Net Income]] -> 0.56182804 | N3: =IF(Global_Household_Financial_Dyna[[#This Row],[Monthly_Savings]]<0,"High Risk", IF(Global_Household_Financial_Dyna[[#This Row],[Savings Rate%]]<0.1, "Medium", "Safe")) -> Safe | O3: =Global_Household_Financial_Dyna[[#This Row],[Total_Household_Income]]/Global_Household_Financial_Dyna[[#This Row],[Family_Size]] -> 2658.285 | P3: =AVERAGEIF($B$2:$B$4986,$B3,$L$2:$L$4986) -> 0.30718717 | Q3: =L3-P3 -> 0.13098479 | R3: =IF(Global_Household_Financial_Dyna[[#This Row],[Vs country_Average]]<-0.2, "Underperformer", IF(Global_Household_Financial_Dyna[[#This Row],[Vs country_Average]]>0.2, "Outperformer", "Normal")) -> Normal | S3: =IF(Global_Household_Financial_Dyna[[#This Row],[Risk_Flag]]="High Risk", Global_Household_Financial_Dyna[[#This Row],[Monthly_Savings]]+(Global_Household_Financial_Dyna[[#This Row],[Net Income]]*Global_Household_Financial_Dyna[[#This Row],[Expense Ratio]]*0.05),Global_Household_Financial_Dyna[[#This Row],[Monthly_Savings]]) -> 1747.18 | T3: =IF(Global_Household_Financial_Dyna[[#This Row],[Risk_Flag]]= "High Risk",Global_Household_Financial_Dyna[[#This Row],[Monthly_Savings]]+Global_Household_Financial_Dyna[[#This Row],[Net Income]]*(Global_Household_Financial_Dyna[[#This Row],[Expense Ratio]]*0.1),Global_Household_Financial_Dyna[[#This Row],[Monthly_Savings]]) -> 1747.18 | U3: =IF(Global_Household_Financial_Dyna[[#This Row],[Risk_Flag]]="High risk",Global_Household_Financial_Dyna[[#This Row],[Monthly_Savings]]+Global_Household_Financial_Dyna[[#This Row],[Net Income]]*(Global_Household_Financial_Dyna[[#This Row],[Expense Ratio]]*0.15),Global_Household_Financial_Dyna[[#This Row],[Monthly_Savings]]) -> 1747.18 | V3: =IF(Global_Household_Financial_Dyna[[#This Row],[Risk_Flag]]="High risk",Global_Household_Financial_Dyna[[#This Row],[Monthly_Savings]]+Global_Household_Financial_Dyna[[#This Row],[Net Income]]*(Global_Household_Financial_Dyna[[#This Row],[Expense Ratio]]*0.2),Global_Household_Financial_Dyna[[#This Row],[Monthly_Savings]]) -> 1747.18
A4: 3 | B4: Brazil | C4: Sao Paulo | D4: 6 | E4: 3 | F4: 827.81 | G4: 2241.32 | H4: 336.2 | I4: 1111.05 | J4: 794.07 | K4: =Global_Household_Financial_Dyna[[#This Row],[Total_Household_Income]]-Global_Household_Financial_Dyna[[#This Row],[Estimated_Taxes]] -> 1905.12 | L4: =Global_Household_Financial_Dyna[[#This Row],[Monthly_Savings]]/Global_Household_Financial_Dyna[[#This Row],[Net Income]] -> 0.41680839 | M4: =Global_Household_Financial_Dyna[[#This Row],[Monthly_Expenses]]/Global_Household_Financial_Dyna[[#This Row],[Net Income]] -> 0.58319161 | N4: =IF(Global_Household_Financial_Dyna[[#This Row],[Monthly_Savings]]<0,"High Risk", IF(Global_Household_Financial_Dyna[[#This Row],[Savings Rate%]]<0.1, "Medium", "Safe")) -> Safe | O4: =Global_Household_Financial_Dyna[[#This Row],[Total_Household_Income]]/Global_Household_Financial_Dyna[[#This Row],[Family_Size]] -> 373.55333 | P4: =AVERAGEIF($B$2:$B$4986,$B4,$L$2:$L$4986) -> 0.39788995 | Q4: =L4-P4 -> 0.018918436 | R4: =IF(Global_Household_Financial_Dyna[[#This Row],[Vs country_Average]]<-0.2, "Underperformer", IF(Global_Household_Financial_Dyna[[#This Row],[Vs country_Average]]>0.2, "Outperformer", "Normal")) -> Normal | S4: =IF(Global_Household_Financial_Dyna[[#This Row],[Risk_Flag]]="High Risk", Global_Household_Financial_Dyna[[#This Row],[Monthly_Savings]]+(Global_Household_Financial_Dyna[[#This Row],[Net Income]]*Global_Household_Financial_Dyna[[#This Row],[Expense Ratio]]*0.05),Global_Household_Financial_Dyna[[#This Row],[Monthly_Savings]]) -> 794.07 | T4: =IF(Global_Household_Financial_Dyna[[#This Row],[Risk_Flag]]= "High Risk",Global_Household_Financial_Dyna[[#This Row],[Monthly_Savings]]+Global_Household_Financial_Dyna[[#This Row],[Net Income]]*(Global_Household_Financial_Dyna[[#This Row],[Expense Ratio]]*0.1),Global_Household_Financial_Dyna[[#This Row],[Monthly_Savings]]) -> 794.07 | U4: =IF(Global_Household_Financial_Dyna[[#This Row],[Risk_Flag]]="High risk",Global_Household_Financial_Dyna[[#This Row],[Monthly_Savings]]+Global_Household_Financial_Dyna[[#This Row],[Net Income]]*(Global_Household_Financial_Dyna[[#This Row],[Expense Ratio]]*0.15),Global_Household_Financial_Dyna[[#This Row],[Monthly_Savings]]) -> 794.07 | V4: =IF(Global_Household_Financial_Dyna[[#This Row],[Risk_Flag]]="High risk",Global_Household_Financial_Dyna[[#This Row],[Monthly_Savings]]+Global_Household_Financial_Dyna[[#This Row],[Net Income]]*(Global_Household_Financial_Dyna[[#This Row],[Expense Ratio]]*0.2),Global_Household_Financial_Dyna[[#This Row],[Monthly_Savings]]) -> 794.07
A5: 4 | B5: Germany | C5: Munich | D5: 4 | E5: 1 | F5: 5139.02 | G5: 5139.02 | H5: 1798.66 | I5: 2922.76 | J5: 417.61 | K5: =Global_Household_Financial_Dyna[[#This Row],[Total_Household_Income]]-Global_Household_Financial_Dyna[[#This Row],[Estimated_Taxes]] -> 3340.36 | L5: =Global_Household_Financial_Dyna[[#This Row],[Monthly_Savings]]/Global_Household_Financial_Dyna[[#This Row],[Net Income]] -> 0.12501946 | M5: =Global_Household_Financial_Dyna[[#This Row],[Monthly_Expenses]]/Global_Household_Financial_Dyna[[#This Row],[Net Income]] -> 0.87498353 | N5: =IF(Global_Household_Financial_Dyna[[#This Row],[Monthly_Savings]]<0,"High Risk", IF(Global_Household_Financial_Dyna[[#This Row],[Savings Rate%]]<0.1, "Medium", "Safe")) -> Safe | O5: =Global_Household_Financial_Dyna[[#This Row],[Total_Household_Income]]/Global_Household_Financial_Dyna[[#This Row],[Family_Size]] -> 1284.755 | P5: =AVERAGEIF($B$2:$B$4986,$B5,$L$2:$L$4986) -> 0.158798 | Q5: =L5-P5 -> -0.03377854 | R5: =IF(Global_Household_Financial_Dyna[[#This Row],[Vs country_Average]]<-0.2, "Underperformer", IF(Global_Household_Financial_Dyna[[#This Row],[Vs country_Average]]>0.2, "Outperformer", "Normal")) -> Normal | S5: =IF(Global_Household_Financial_Dyna[[#This Row],[Risk_Flag]]="High Risk", Global_Household_Financial_Dyna[[#This Row],[Monthly_Savings]]+(Global_Household_Financial_Dyna[[#This Row],[Net Income]]*Global_Household_Financial_Dyna[[#This Row],[Expense Ratio]]*0.05),Global_Household_Financial_Dyna[[#This Row],[Monthly_Savings]]) -> 417.61 | T5: =IF(Global_Household_Financial_Dyna[[#This Row],[Risk_Flag]]= "High Risk",Global_Household_Financial_Dyna[[#This Row],[Monthly_Savings]]+Global_Household_Financial_Dyna[[#This Row],[Net Income]]*(Global_Household_Financial_Dyna[[#This Row],[Expense Ratio]]*0.1),Global_Household_Financial_Dyna[[#This Row],[Monthly_Savings]]) -> 417.61 | U5: =IF(Global_Household_Financial_Dyna[[#This Row],[Risk_Flag]]="High risk",Global_Household_Financial_Dyna[[#This Row],[Monthly_Savings]]+Global_Household_Financial_Dyna[[#This Row],[Net Income]]*(Global_Household_Financial_Dyna[[#This Row],[Expense Ratio]]*0.15),Global_Household_Financial_Dyna[[#This Row],[Monthly_Savings]]) -> 417.61 | V5: =IF(Global_Household_Financial_Dyna[[#This Row],[Risk_Flag]]="High risk",Global_Household_Financial_Dyna[[#This Row],[Monthly_Savings]]+Global_Household_Financial_Dyna[[#This Row],[Net Income]]*(Global_Household_Financial_Dyna[[#This Row],[Expense Ratio]]*0.2),Global_Household_Financial_Dyna[[#This Row],[Monthly_Savings]]) -> 417.61
A6: 5 | B6: USA | C6: New York | D6: 4 | E6: 3 | F6: 4506.74 | G6: 9624.55 | H6: 2598.63 | I6: 2910.88 | J6: 4115.04 | K6: =Global_Household_Financial_Dyna[[#This Row],[Total_Household_Income]]-Global_Household_Financial_Dyna[[#This Row],[Estimated_Taxes]] -> 7025.92 | L6: =Global_Household_Financial_Dyna[[#This Row],[Monthly_Savings]]/Global_Household_Financial_Dyna[[#This Row],[Net Income]] -> 0.58569412 | M6: =Global_Household_Financial_Dyna[[#This Row],[Monthly_Expenses]]/Global_Household_Financial_Dyna[[#This Row],[Net Income]] -> 0.41430588 | N6: =IF(Global_Household_Financial_Dyna[[#This Row],[Monthly_Savings]]<0,"High Risk", IF(Global_Household_Financial_Dyna[[#This Row],[Savings Rate%]]<0.1, "Medium", "Safe")) -> Safe | O6: =Global_Household_Financial_Dyna[[#This Row],[Total_Household_Income]]/Global_Household_Financial_Dyna[[#This Row],[Family_Size]] -> 2406.1375 | P6: =AVERAGEIF($B$2:$B$4986,$B6,$L$2:$L$4986) -> 0.32336205 | Q6: =L6-P6 -> 0.26233207 | R6: =IF(Global_Household_Financial_Dyna[[#This Row],[Vs country_Average]]<-0.2, "Underperformer", IF(Global_Household_Financial_Dyna[[#This Row],[Vs country_Average]]>0.2, "Outperformer", "Normal")) -> Outperformer | S6: =IF(Global_Household_Financial_Dyna[[#This Row],[Risk_Flag]]="High Risk", Global_Household_Financial_Dyna[[#This Row],[Monthly_Savings]]+(Global_Household_Financial_Dyna[[#This Row],[Net Income]]*Global_Household_Financial_Dyna[[#This Row],[Expense Ratio]]*0.05),Global_Household_Financial_Dyna[[#This Row],[Monthly_Savings]]) -> 4115.04 | T6: =IF(Global_Household_Financial_Dyna[[#This Row],[Risk_Flag]]= "High Risk",Global_Household_Financial_Dyna[[#This Row],[Monthly_Savings]]+Global_Household_Financial_Dyna[[#This Row],[Net Income]]*(Global_Household_Financial_Dyna[[#This Row],[Expense Ratio]]*0.1),Global_Household_Financial_Dyna[[#This Row],[Monthly_Savings]]) -> 4115.04 | U6: =IF(Global_Household_Financial_Dyna[[#This Row],[Risk_Flag]]="High risk",Global_Household_Financial_Dyna[[#This Row],[Monthly_Savings]]+Global_Household_Financial_Dyna[[#This Row],[Net Income]]*(Global_Household_Financial_Dyna[[#This Row],[Expense Ratio]]*0.15),Global_Household_Financial_Dyna[[#This Row],[Monthly_Savings]]) -> 4115.04 | V6: =IF(Global_Household_Financial_Dyna[[#This Row],[Risk_Flag]]="High risk",Global_Household_Financial_Dyna[[#This Row],[Monthly_Savings]]+Global_Household_Financial_Dyna[[#This Row],[Net Income]]*(Global_Household_Financial_Dyna[[#This Row],[Expense Ratio]]*0.2),Global_Household_Financial_Dyna[[#This Row],[Monthly_Savings]]) -> 4115.04
A7: 6 | B7: USA | C7: Chicago | D7: 5 | E7: 2 | F7: 4536.89 | G7: 7235.89 | H7: 1591.9 | I7: 2437.1 | J7: 3206.89 | K7: =Global_Household_Financial_Dyna[[#This Row],[Total_Household_Income]]-Global_Household_Financial_Dyna[[#This Row],[Estimated_Taxes]] -> 5643.99 | L7: =Global_Household_Financial_Dyna[[#This Row],[Monthly_Savings]]/Global_Household_Financial_Dyna[[#This Row],[Net Income]] -> 0.56819555 | M7: =Global_Household_Financial_Dyna[[#This Row],[Monthly_Expenses]]/Global_Household_Financial_Dyna[[#This Row],[Net Income]] -> 0.43180445 | N7: =IF(Global_Household_Financial_Dyna[[#This Row],[Monthly_Savings]]<0,"High Risk", IF(Global_Household_Financial_Dyna[[#This Row],[Savings Rate%]]<0.1, "Medium", "Safe")) -> Safe | O7: =Global_Household_Financial_Dyna[[#This Row],[Total_Household_Income]]/Global_Household_Financial_Dyna[[#This Row],[Family_Size]] -> 1447.178 | P7: =AVERAGEIF($B$2:$B$4986,$B7,$L$2:$L$4986) -> 0.32336205 | Q7: =L7-P7 -> 0.2448335 | R7: =IF(Global_Household_Financial_Dyna[[#This Row],[Vs country_Average]]<-0.2, "Underperformer", IF(Global_Household_Financial_Dyna[[#This Row],[Vs country_Average]]>0.2, "Outperformer", "Normal")) -> Outperformer | S7: =IF(Global_Household_Financial_Dyna[[#This Row],[Risk_Flag]]="High Risk", Global_Household_Financial_Dyna[[#This Row],[Monthly_Savings]]+(Global_Household_Financial_Dyna[[#This Row],[Net Income]]*Global_Household_Financial_Dyna[[#This Row],[Expense Ratio]]*0.05),Global_Household_Financial_Dyna[[#This Row],[Monthly_Savings]]) -> 3206.89 | T7: =IF(Global_Household_Financial_Dyna[[#This Row],[Risk_Flag]]= "High Risk",Global_Household_Financial_Dyna[[#This Row],[Monthly_Savings]]+Global_Household_Financial_Dyna[[#This Row],[Net Income]]*(Global_Household_Financial_Dyna[[#This Row],[Expense Ratio]]*0.1),Global_Household_Financial_Dyna[[#This Row],[Monthly_Savings]]) -> 3206.89 | U7: =IF(Global_Household_Financial_Dyna[[#This Row],[Risk_Flag]]="High risk",Global_Household_Financial_Dyna[[#This Row],[Monthly_Savings]]+Global_Household_Financial_Dyna[[#This Row],[Net Income]]*(Global_Household_Financial_Dyna[[#This Row],[Expense Ratio]]*0.15),Global_Household_Financial_Dyna[[#This Row],[Monthly_Savings]]) -> 3206.89 | V7: =IF(Global_Household_Financial_Dyna[[#This Row],[Risk_Flag]]="High risk",Global_Household_Financial_Dyna[[#This Row],[Monthly_Savings]]+Global_Household_Financial_Dyna[[#This Row],[Net Income]]*(Global_Household_Financial_Dyna[[#This Row],[Expense Ratio]]*0.2),Global_Household_Financial_Dyna[[#This Row],[Monthly_Savings]]) -> 3206.89
A8: 7 | B8: USA | C8: Chicago | D8: 7 | E8: 3 | F8: 3957.13 | G8: 8172.73 | H8: 2206.64 | I8: 4197.44 | J8: 1768.65 | K8: =Global_Household_Financial_Dyna[[#This Row],[Total_Household_Income]]-Global_Household_Financial_Dyna[[#This Row],[Estimated_Taxes]] -> 5966.09 | L8: =Global_Household_Financial_Dyna[[#This Row],[Monthly_Savings]]/Global_Household_Financial_Dyna[[#This Row],[Net Income]] -> 0.29645044 | M8: =Global_Household_Financial_Dyna[[#This Row],[Monthly_Expenses]]/Global_Household_Financial_Dyna[[#This Row],[Net Income]] -> 0.70354956 | N8: =IF(Global_Household_Financial_Dyna[[#This Row],[Monthly_Savings]]<0,"High Risk", IF(Global_Household_Financial_Dyna[[#This Row],[Savings Rate%]]<0.1, "Medium", "Safe")) -> Safe | O8: =Global_Household_Financial_Dyna[[#This Row],[Total_Household_Income]]/Global_Household_Financial_Dyna[[#This Row],[Family_Size]] -> 1167.5329 | P8: =AVERAGEIF($B$2:$B$4986,$B8,$L$2:$L$4986) -> 0.32336205 | Q8: =L8-P8 -> -0.02691161 | R8: =IF(Global_Household_Financial_Dyna[[#This Row],[Vs country_Average]]<-0.2, "Underperformer", IF(Global_Household_Financial_Dyna[[#This Row],[Vs country_Average]]>0.2, "Outperformer", "Normal")) -> Normal | S8: =IF(Global_Household_Financial_Dyna[[#This Row],[Risk_Flag]]="High Risk", Global_Household_Financial_Dyna[[#This Row],[Monthly_Savings]]+(Global_Household_Financial_Dyna[[#This Row],[Net Income]]*Global_Household_Financial_Dyna[[#This Row],[Expense Ratio]]*0.05),Global_Household_Financial_Dyna[[#This Row],[Monthly_Savings]]) -> 1768.65 | T8: =IF(Global_Household_Financial_Dyna[[#This Row],[Risk_Flag]]= "High Risk",Global_Household_Financial_Dyna[[#This Row],[Monthly_Savings]]+Global_Household_Financial_Dyna[[#This Row],[Net Income]]*(Global_Household_Financial_Dyna[[#This Row],[Expense Ratio]]*0.1),Global_Household_Financial_Dyna[[#This Row],[Monthly_Savings]]) -> 1768.65 | U8: =IF(Global_Household_Financial_Dyna[[#This Row],[Risk_Flag]]="High risk",Global_Household_Financial_Dyna[[#This Row],[Monthly_Savings]]+Global_Household_Financial_Dyna[[#This Row],[Net Income]]*(Global_Household_Financial_Dyna[[#This Row],[Expense Ratio]]*0.15),Global_Household_Financial_Dyna[[#This Row],[Monthly_Savings]]) -> 1768.65 | V8: =IF(Global_Household_Financial_Dyna[[#This Row],[Risk_Flag]]="High risk",Global_Household_Financial_Dyna[[#This Row],[Monthly_Savings]]+Global_Household_Financial_Dyna[[#This Row],[Net Income]]*(Global_Household_Financial_Dyna[[#This Row],[Expense Ratio]]*0.2),Global_Household_Financial_Dyna[[#This Row],[Monthly_Savings]]) -> 1768.65
A9: 8 | B9: UK | C9: London | D9: 8 | E9: 2 | F9: 3568.25 | G9: 5214.34 | H9: 1303.58 | I9: 4948.41 | J9: -1037.65 | K9: =Global_Household_Financial_Dyna[[#This Row],[Total_Household_Income]]-Global_Household_Financial_Dyna[[#This Row],[Estimated_Taxes]] -> 3910.76 | L9: =Global_Household_Financial_Dyna[[#This Row],[Monthly_Savings]]/Global_Household_Financial_Dyna[[#This Row],[Net Income]] -> -0.26533206 | M9: =Global_Household_Financial_Dyna[[#This Row],[Monthly_Expenses]]/Global_Household_Financial_Dyna[[#This Row],[Net Income]] -> 1.2653321 | N9: =IF(Global_Household_Financial_Dyna[[#This Row],[Monthly_Savings]]<0,"High Risk", IF(Global_Household_Financial_Dyna[[#This Row],[Savings Rate%]]<0.1, "Medium", "Safe")) -> High Risk | O9: =Global_Household_Financial_Dyna[[#This Row],[Total_Household_Income]]/Global_Household_Financial_Dyna[[#This Row],[Family_Size]] -> 651.7925 | P9: =AVERAGEIF($B$2:$B$4986,$B9,$L$2:$L$4986) -> 0.30718717 | Q9: =L9-P9 -> -0.57251923 | R9: =IF(Global_Household_Financial_Dyna[[#This Row],[Vs country_Average]]<-0.2, "Underperformer", IF(Global_Household_Financial_Dyna[[#This Row],[Vs country_Average]]>0.2, "Outperformer", "Normal")) -> Underperformer | S9: =IF(Global_Household_Financial_Dyna[[#This Row],[Risk_Flag]]="High Risk", Global_Household_Financial_Dyna[[#This Row],[Monthly_Savings]]+(Global_Household_Financial_Dyna[[#This Row],[Net Income]]*Global_Household_Financial_Dyna[[#This Row],[Expense Ratio]]*0.05),Global_Household_Financial_Dyna[[#This Row],[Monthly_Savings]]) -> -790.2295 | T9: =IF(Global_Household_Financial_Dyna[[#This Row],[Risk_Flag]]= "High Risk",Global_Household_Financial_Dyna[[#This Row],[Monthly_Savings]]+Global_Household_Financial_Dyna[[#This Row],[Net Income]]*(Global_Household_Financial_Dyna[[#This Row],[Expense Ratio]]*0.1),Global_Household_Financial_Dyna[[#This Row],[Monthly_Savings]]) -> -542.809 | U9: =IF(Global_Household_Financial_Dyna[[#This Row],[Risk_Flag]]="High risk",Global_Household_Financial_Dyna[[#This Row],[Monthly_Savings]]+Global_Household_Financial_Dyna[[#This Row],[Net Income]]*(Global_Household_Financial_Dyna[[#This Row],[Expense Ratio]]*0.15),Global_Household_Financial_Dyna[[#This Row],[Monthly_Savings]]) -> -295.3885 | V9: =IF(Global_Household_Financial_Dyna[[#This Row],[Risk_Flag]]="High risk",Global_Household_Financial_Dyna[[#This Row],[Monthly_Savings]]+Global_Household_Financial_Dyna[[#This Row],[Net Income]]*(Global_Household_Financial_Dyna[[#This Row],[Expense Ratio]]*0.2),Global_Household_Financial_Dyna[[#This Row],[Monthly_Savings]]) -> -47.968
A10: 9 | B10: Germany | C10: Berlin | D10: 2 | E10: 2 | F10: 5277.68 | G10: 7838.3 | H10: 2743.4 | I10: 2485.94 | J10: 2608.95 | K10: =Global_Household_Financial_Dyna[[#This Row],[Total_Household_Income]]-Global_Household_Financial_Dyna[[#This Row],[Estimated_Taxes]] -> 5094.9 | L10: =Global_Household_Financial_Dyna[[#This Row],[Monthly_Savings]]/Global_Household_Financial_Dyna[[#This Row],[Net Income]] -> 0.51207089 | M10: =Global_Household_Financial_Dyna[[#This Row],[Monthly_Expenses]]/Global_Household_Financial_Dyna[[#This Row],[Net Income]] -> 0.48792714 | N10: =IF(Global_Household_Financial_Dyna[[#This Row],[Monthly_Savings]]<0,"High Risk", IF(Global_Household_Financial_Dyna[[#This Row],[Savings Rate%]]<0.1, "Medium", "Safe")) -> Safe | O10: =Global_Household_Financial_Dyna[[#This Row],[Total_Household_Income]]/Global_Household_Financial_Dyna[[#This Row],[Family_Size]] -> 3919.15 | P10: =AVERAGEIF($B$2:$B$4986,$B10,$L$2:$L$4986) -> 0.158798 | Q10: =L10-P10 -> 0.3532729 | R10: =IF(Global_Household_Financial_Dyna[[#This Row],[Vs country_Average]]<-0.2, "Underperformer", IF(Global_Household_Financial_Dyna[[#This Row],[Vs country_Average]]>0.2, "Outperformer", "Normal")) -> Outperformer | S10: =IF(Global_Household_Financial_Dyna[[#This Row],[Risk_Flag]]="High Risk", Global_Household_Financial_Dyna[[#This Row],[Monthly_Savings]]+(Global_Household_Financial_Dyna[[#This Row],[Net Income]]*Global_Household_Financial_Dyna[[#This Row],[Expense Ratio]]*0.05),Global_Household_Financial_Dyna[[#This Row],[Monthly_Savings]]) -> 2608.95 | T10: =IF(Global_Household_Financial_Dyna[[#This Row],[Risk_Flag]]= "High Risk",Global_Household_Financial_Dyna[[#This Row],[Monthly_Savings]]+Global_Household_Financial_Dyna[[#This Row],[Net Income]]*(Global_Household_Financial_Dyna[[#This Row],[Expense Ratio]]*0.1),Global_Household_Financial_Dyna[[#This Row],[Monthly_Savings]]) -> 2608.95 | U10: =IF(Global_Household_Financial_Dyna[[#This Row],[Risk_Flag]]="High risk",Global_Household_Financial_Dyna[[#This Row],[Monthly_Savings]]+Global_Household_Financial_Dyna[[#This Row],[Net Income]]*(Global_Household_Financial_Dyna[[#This Row],[Expense Ratio]]*0.15),Global_Household_Financial_Dyna[[#This Row],[Monthly_Savings]]) -> 2608.95 | V10: =IF(Global_Household_Financial_Dyna[[#This Row],[Risk_Flag]]="High risk",Global_Household_Financial_Dyna[[#This Row],[Monthly_Savings]]+Global_Household_Financial_Dyna[[#This Row],[Net Income]]*(Global_Household_Financial_Dyna[[#This Row],[Expense Ratio]]*0.2),Global_Household_Financial_Dyna[[#This Row],[Monthly_Savings]]) -> 2608.95
A11: 10 | B11: Brazil | C11: Sao Paulo | D11: 4 | E11: 3 | F11: 1256.63 | G11: 2425.63 | H11: 363.85 | I11: 902.75 | J11: 1159.04 | K11: =Global_Household_Financial_Dyna[[#This Row],[Total_Household_Income]]-Global_Household_Financial_Dyna[[#This Row],[Estimated_Taxes]] -> 2061.78 | L11: =Global_Household_Financial_Dyna[[#This Row],[Monthly_Savings]]/Global_Household_Financial_Dyna[[#This Row],[Net Income]] -> 0.56215503 | M11: =Global_Household_Financial_Dyna[[#This Row],[Monthly_Expenses]]/Global_Household_Financial_Dyna[[#This Row],[Net Income]] -> 0.43784982 | N11: =IF(Global_Household_Financial_Dyna[[#This Row],[Monthly_Savings]]<0,"High Risk", IF(Global_Household_Financial_Dyna[[#This Row],[Savings Rate%]]<0.1, "Medium", "Safe")) -> Safe | O11: =Global_Household_Financial_Dyna[[#This Row],[Total_Household_Income]]/Global_Household_Financial_Dyna[[#This Row],[Family_Size]] -> 606.4075 | P11: =AVERAGEIF($B$2:$B$4986,$B11,$L$2:$L$4986) -> 0.39788995 | Q11: =L11-P11 -> 0.16426508 | R11: =IF(Global_Household_Financial_Dyna[[#This Row],[Vs country_Average]]<-0.2, "Underperformer", IF(Global_Household_Financial_Dyna[[#This Row],[Vs country_Average]]>0.2, "Outperformer", "Normal")) -> Normal | S11: =IF(Global_Household_Financial_Dyna[[#This Row],[Risk_Flag]]="High Risk", Global_Household_Financial_Dyna[[#This Row],[Monthly_Savings]]+(Global_Household_Financial_Dyna[[#This Row],[Net Income]]*Global_Household_Financial_Dyna[[#This Row],[Expense Ratio]]*0.05),Global_Household_Financial_Dyna[[#This Row],[Monthly_Savings]]) -> 1159.04 | T11: =IF(Global_Household_Financial_Dyna[[#This Row],[Risk_Flag]]= "High Risk",Global_Household_Financial_Dyna[[#This Row],[Monthly_Savings]]+Global_Household_Financial_Dyna[[#This Row],[Net Income]]*(Global_Household_Financial_Dyna[[#This Row],[Expense Ratio]]*0.1),Global_Household_Financial_Dyna[[#This Row],[Monthly_Savings]]) -> 1159.04 | U11: =IF(Global_Household_Financial_Dyna[[#This Row],[Risk_Flag]]="High risk",Global_Household_Financial_Dyna[[#This Row],[Monthly_Savings]]+Global_Household_Financial_Dyna[[#This Row],[Net Income]]*(Global_Household_Financial_Dyna[[#This Row],[Expense Ratio]]*0.15),Global_Household_Financial_Dyna[[#This Row],[Monthly_Savings]]) -> 1159.04 | V11: =IF(Global_Household_Financial_Dyna[[#This Row],[Risk_Flag]]="High risk",Global_Household_Financial_Dyna[[#This Row],[Monthly_Savings]]+Global_Household_Financial_Dyna[[#This Row],[Net Income]]*(Global_Household_Financial_Dyna[[#This Row],[Expense Ratio]]*0.2),Global_Household_Financial_Dyna[[#This Row],[Monthly_Savings]]) -> 1159.04
A12: 11 | B12: USA | C12: Chicago | D12: 8 | E12: 3 | F12: 3240.5 | G12: 7497.82 | H12: 1649.52 | I12: 5856.22 | J12: -7.92 | K12: =Global_Household_Financial_Dyna[[#This Row],[Total_Household_Income]]-Global_Household_Financial_Dyna[[#This Row],[Estimated_Taxes]] -> 5848.3 | L12: =Global_Household_Financial_Dyna[[#This Row],[Monthly_Savings]]/Global_Household_Financial_Dyna[[#This Row],[Net Income]] -> -0.0013542397 | M12: =Global_Household_Financial_Dyna[[#This Row],[Monthly_Expenses]]/Global_Household_Financial_Dyna[[#This Row],[Net Income]] -> 1.0013542 | N12: =IF(Global_Household_Financial_Dyna[[#This Row],[Monthly_Savings]]<0,"High Risk", IF(Global_Household_Financial_Dyna[[#This Row],[Savings Rate%]]<0.1, "Medium", "Safe")) -> High Risk | O12: =Global_Household_Financial_Dyna[[#This Row],[Total_Household_Income]]/Global_Household_Financial_Dyna[[#This Row],[Family_Size]] -> 937.2275 | P12: =AVERAGEIF($B$2:$B$4986,$B12,$L$2:$L$4986) -> 0.32336205 | Q12: =L12-P12 -> -0.32471629 | R12: =IF(Global_Household_Financial_Dyna[[#This Row],[Vs country_Average]]<-0.2, "Underperformer", IF(Global_Household_Financial_Dyna[[#This Row],[Vs country_Average]]>0.2, "Outperformer", "Normal")) -> Underperformer | S12: =IF(Global_Household_Financial_Dyna[[#This Row],[Risk_Flag]]="High Risk", Global_Household_Financial_Dyna[[#This Row],[Monthly_Savings]]+(Global_Household_Financial_Dyna[[#This Row],[Net Income]]*Global_Household_Financial_Dyna[[#This Row],[Expense Ratio]]*0.05),Global_Household_Financial_Dyna[[#This Row],[Monthly_Savings]]) -> 284.891 | T12: =IF(Global_Household_Financial_Dyna[[#This Row],[Risk_Flag]]= "High Risk",Global_Household_Financial_Dyna[[#This Row],[Monthly_Savings]]+Global_Household_Financial_Dyna[[#This Row],[Net Income]]*(Global_Household_Financial_Dyna[[#This Row],[Expense Ratio]]*0.1),Global_Household_Financial_Dyna[[#This Row],[Monthly_Savings]]) -> 577.702 | U12: =IF(Global_Household_Financial_Dyna[[#This Row],[Risk_Flag]]="High risk",Global_Household_Financial_Dyna[[#This Row],[Monthly_Savings]]+Global_Household_Financial_Dyna[[#This Row],[Net Income]]*(Global_Household_Financial_Dyna[[#This Row],[Expense Ratio]]*0.15),Global_Household_Financial_Dyna[[#This Row],[Monthly_Savings]]) -> 870.513 | V12: =IF(Global_Household_Financial_Dyna[[#This Row],[Risk_Flag]]="High risk",Global_Household_Financial_Dyna[[#This Row],[Monthly_Savings]]+Global_Household_Financial_Dyna[[#This Row],[Net Income]]*(Global_Household_Financial_Dyna[[#This Row],[Expense Ratio]]*0.2),Global_Household_Financial_Dyna[[#This Row],[Monthly_Savings]]) -> 1163.324
A13: 12 | B13: UK | C13: London | D13: 5 | E13: 3 | F13: 5768.09 | G13: 12306.86 | H13: 3692.06 | I13: 3665.66 | J13: 4949.14 | K13: =Global_Household_Financial_Dyna[[#This Row],[Total_Household_Income]]-Global_Household_Financial_Dyna[[#This Row],[Estimated_Taxes]] -> 8614.8 | L13: =Global_Household_Financial_Dyna[[#This Row],[Monthly_Savings]]/Global_Household_Financial_Dyna[[#This Row],[Net Income]] -> 0.57449273 | M13: =Global_Household_Financial_Dyna[[#This Row],[Monthly_Expenses]]/Global_Household_Financial_Dyna[[#This Row],[Net Income]] -> 0.42550727 | N13: =IF(Global_Household_Financial_Dyna[[#This Row],[Monthly_Savings]]<0,"High Risk", IF(Global_Household_Financial_Dyna[[#This Row],[Savings Rate%]]<0.1, "Medium", "Safe")) -> Safe | O13: =Global_Household_Financial_Dyna[[#This Row],[Total_Household_Income]]/Global_Household_Financial_Dyna[[#This Row],[Family_Size]] -> 2461.372 | P13: =AVERAGEIF($B$2:$B$4986,$B13,$L$2:$L$4986) -> 0.30718717 | Q13: =L13-P13 -> 0.26730557 | R13: =IF(Global_Household_Financial_Dyna[[#This Row],[Vs country_Average]]<-0.2, "Underperformer", IF(Global_Household_Financial_Dyna[[#This Row],[Vs country_Average]]>0.2, "Outperformer", "Normal")) -> Outperformer | S13: =IF(Global_Household_Financial_Dyna[[#This Row],[Risk_Flag]]="High Risk", Global_Household_Financial_Dyna[[#This Row],[Monthly_Savings]]+(Global_Household_Financial_Dyna[[#This Row],[Net Income]]*Global_Household_Financial_Dyna[[#This Row],[Expense Ratio]]*0.05),Global_Household_Financial_Dyna[[#This Row],[Monthly_Savings]]) -> 4949.14 | T13: =IF(Global_Household_Financial_Dyna[[#This Row],[Risk_Flag]]= "High Risk",Global_Household_Financial_Dyna[[#This Row],[Monthly_Savings]]+Global_Household_Financial_Dyna[[#This Row],[Net Income]]*(Global_Household_Financial_Dyna[[#This Row],[Expense Ratio]]*0.1),Global_Household_Financial_Dyna[[#This Row],[Monthly_Savings]]) -> 4949.14 | U13: =IF(Global_Household_Financial_Dyna[[#This Row],[Risk_Flag]]="High risk",Global_Household_Financial_Dyna[[#This Row],[Monthly_Savings]]+Global_Household_Financial_Dyna[[#This Row],[Net Income]]*(Global_Household_Financial_Dyna[[#This Row],[Expense Ratio]]*0.15),Global_Household_Financial_Dyna[[#This Row],[Monthly_Savings]]) -> 4949.14 | V13: =IF(Global_Household_Financial_Dyna[[#This Row],[Risk_Flag]]="High risk",Global_Household_Financial_Dyna[[#This Row],[Monthly_Savings]]+Global_Household_Financial_Dyna[[#This Row],[Net Income]]*(Global_Household_Financial_Dyna[[#This Row],[Expense Ratio]]*0.2),Global_Household_Financial_Dyna[[#This Row],[Monthly_Savings]]) -> 4949.14
... A4986: 5000 | B4986: Germany | C4986: Munich | D4986: 1 | E4986: 1 | F4986: 5021.42 | G4986: 5021.42 | H4986: 1757.5 | I4986: 1257.14 | J4986: 2006.78 | K4986: =Global_Household_Financial_Dyna[[#This Row],[Total_Household_Income]]-Global_Household_Financial_Dyna[[#This Row],[Estimated_Taxes]] -> 3263.92 | L4986: =Global_Household_Financial_Dyna[[#This Row],[Monthly_Savings]]/Global_Household_Financial_Dyna[[#This Row],[Net Income]] -> 0.61483737 | M4986: =Global_Household_Financial_Dyna[[#This Row],[Monthly_Expenses]]/Global_Household_Financial_Dyna[[#This Row],[Net Income]] -> 0.38516263 | N4986: =IF(Global_Household_Financial_Dyna[[#This Row],[Monthly_Savings]]<0,"High Risk", IF(Global_Household_Financial_Dyna[[#This Row],[Savings Rate%]]<0.1, "Medium", "Safe")) -> Safe | O4986: =Global_Household_Financial_Dyna[[#This Row],[Total_Household_Income]]/Global_Household_Financial_Dyna[[#This Row],[Family_Size]] -> 5021.42 | P4986: =AVERAGEIF($B$2:$B$4986,$B4986,$L$2:$L$4986) -> 0.158798 | Q4986: =L4986-P4986 -> 0.45603937 | R4986: =IF(Global_Household_Financial_Dyna[[#This Row],[Vs country_Average]]<-0.2, "Underperformer", IF(Global_Household_Financial_Dyna[[#This Row],[Vs country_Average]]>0.2, "Outperformer", "Normal")) -> Outperformer | S4986: =IF(Global_Household_Financial_Dyna[[#This Row],[Risk_Flag]]="High Risk", Global_Household_Financial_Dyna[[#This Row],[Monthly_Savings]]+(Global_Household_Financial_Dyna[[#This Row],[Net Income]]*Global_Household_Financial_Dyna[[#This Row],[Expense Ratio]]*0.05),Global_Household_Financial_Dyna[[#This Row],[Monthly_Savings]]) -> 2006.78 | T4986: =IF(Global_Household_Financial_Dyna[[#This Row],[Risk_Flag]]= "High Risk",Global_Household_Financial_Dyna[[#This Row],[Monthly_Savings]]+Global_Household_Financial_Dyna[[#This Row],[Net Income]]*(Global_Household_Financial_Dyna[[#This Row],[Expense Ratio]]*0.1),Global_Household_Financial_Dyna[[#This Row],[Monthly_Savings]]) -> 2006.78 | U4986: =IF(Global_Household_Financial_Dyna[[#This Row],[Risk_Flag]]="High risk",Global_Household_Financial_Dyna[[#This Row],[Monthly_Savings]]+Global_Household_Financial_Dyna[[#This Row],[Net Income]]*(Global_Household_Financial_Dyna[[#This Row],[Expense Ratio]]*0.15),Global_Household_Financial_Dyna[[#This Row],[Monthly_Savings]]) -> 2006.78 | V4986: =IF(Global_Household_Financial_Dyna[[#This Row],[Risk_Flag]]="High risk",Global_Household_Financial_Dyna[[#This Row],[Monthly_Savings]]+Global_Household_Financial_Dyna[[#This Row],[Net Income]]*(Global_Household_Financial_Dyna[[#This Row],[Expense Ratio]]*0.2),Global_Household_Financial_Dyna[[#This Row],[Monthly_Savings]]) -> 2006.78

Sheet Advance Analysis
A1: Country | B1: High risk count | C1: Country benchmark(AVG Savings Rate) | D1: AVG Net Income | E1: Total Households | F1: Underperformer_count
A2: Brazil | B2: =COUNTIFS('STEP-2 CLEANED_DATA_ FROM_POWER'!B:B,"Brazil",'STEP-2 CLEANED_DATA_ FROM_POWER'!N:N,"High Risk") -> 102 | C2: =AVERAGEIF('STEP-2 CLEANED_DATA_ FROM_POWER'!B:B,'Advance Analysis'!A2,'STEP-2 CLEANED_DATA_ FROM_POWER'!L:L) -> 0.39788995 | D2: =AVERAGEIF('STEP-2 CLEANED_DATA_ FROM_POWER'!B:B,'Advance Analysis'!A2,'STEP-2 CLEANED_DATA_ FROM_POWER'!K:K) -> 2251.7127 | E2: =COUNTIF('STEP-2 CLEANED_DATA_ FROM_POWER'!B:B,'Advance Analysis'!A2) -> 738 | F2: =COUNTIFS('STEP-2 CLEANED_DATA_ FROM_POWER'!B:B,"Brazil",'STEP-2 CLEANED_DATA_ FROM_POWER'!R:R,"Underperformer") -> 161
A3: Germany | B3: =COUNTIFS('STEP-2 CLEANED_DATA_ FROM_POWER'!B:B,"Germany",'STEP-2 CLEANED_DATA_ FROM_POWER'!N:N,"High Risk") -> 313 | C3: =AVERAGEIF('STEP-2 CLEANED_DATA_ FROM_POWER'!B:B,'Advance Analysis'!A3,'STEP-2 CLEANED_DATA_ FROM_POWER'!L:L) -> 0.158798 | D3: =AVERAGEIF('STEP-2 CLEANED_DATA_ FROM_POWER'!B:B,'Advance Analysis'!A3,'STEP-2 CLEANED_DATA_ FROM_POWER'!K:K) -> 4456.549 | E3: =COUNTIF('STEP-2 CLEANED_DATA_ FROM_POWER'!B:B,'Advance Analysis'!A3) -> 1028 | F3: =COUNTIFS('STEP-2 CLEANED_DATA_ FROM_POWER'!B:B,"Germany",'STEP-2 CLEANED_DATA_ FROM_POWER'!R:R,"Underperformer") -> 290
A4: India | B4: =COUNTIFS('STEP-2 CLEANED_DATA_ FROM_POWER'!B:B,"India",'STEP-2 CLEANED_DATA_ FROM_POWER'!N:N,"High Risk") -> 170 | C4: =AVERAGEIF('STEP-2 CLEANED_DATA_ FROM_POWER'!B:B,'Advance Analysis'!A4,'STEP-2 CLEANED_DATA_ FROM_POWER'!L:L) -> 0.42077342 | D4: =AVERAGEIF('STEP-2 CLEANED_DATA_ FROM_POWER'!B:B,'Advance Analysis'!A4,'STEP-2 CLEANED_DATA_ FROM_POWER'!K:K) -> 1210.9298 | E4: =COUNTIF('STEP-2 CLEANED_DATA_ FROM_POWER'!B:B,'Advance Analysis'!A4) -> 1212 | F4: =COUNTIFS('STEP-2 CLEANED_DATA_ FROM_POWER'!B:B,"India",'STEP-2 CLEANED_DATA_ FROM_POWER'!R:R,"Underperformer") -> 299
A5: UK | B5: =COUNTIFS('STEP-2 CLEANED_DATA_ FROM_POWER'!B:B,"UK",'STEP-2 CLEANED_DATA_ FROM_POWER'!N:N,"High Risk") -> 148 | C5: =AVERAGEIF('STEP-2 CLEANED_DATA_ FROM_POWER'!B:B,'Advance Analysis'!A5,'STEP-2 CLEANED_DATA_ FROM_POWER'!L:L) -> 0.30718717 | D5: =AVERAGEIF('STEP-2 CLEANED_DATA_ FROM_POWER'!B:B,'Advance Analysis'!A5,'STEP-2 CLEANED_DATA_ FROM_POWER'!K:K) -> 5108.415 | E5: =COUNTIF('STEP-2 CLEANED_DATA_ FROM_POWER'!B:B,'Advance Analysis'!A5) -> 727 | F5: =COUNTIFS('STEP-2 CLEANED_DATA_ FROM_POWER'!B:B,"UK",'STEP-2 CLEANED_DATA_ FROM_POWER'!R:R,"Underperformer") -> 183
A6: USA | B6: =COUNTIFS('STEP-2 CLEANED_DATA_ FROM_POWER'!B:B,"USA",'STEP-2 CLEANED_DATA_ FROM_POWER'!N:N,"High Risk") -> 233 | C6: =AVERAGEIF('STEP-2 CLEANED_DATA_ FROM_POWER'!B:B,'Advance Analysis'!A6,'STEP-2 CLEANED_DATA_ FROM_POWER'!L:L) -> 0.32336205 | D6: =AVERAGEIF('STEP-2 CLEANED_DATA_ FROM_POWER'!B:B,'Advance Analysis'!A6,'STEP-2 CLEANED_DATA_ FROM_POWER'!K:K) -> 5039.2985 | E6: =COUNTIF('STEP-2 CLEANED_DATA_ FROM_POWER'!B:B,'Advance Analysis'!A6) -> 1280 | F6: =COUNTIFS('STEP-2 CLEANED_DATA_ FROM_POWER'!B:B,"USA",'STEP-2 CLEANED_DATA_ FROM_POWER'!R:R,"Underperformer") -> 318

Sheet Global_Household_Financial_Dyna
A1: Household_ID | B1: Country | C1: City | D1: Family_Size | E1: Num_Earners | F1: Primary_Income | G1: Total_Household_Income | H1: Estimated_Taxes | I1: Monthly_Expenses | J1: Monthly_Savings
A2: 1 | B2: India | C2: Mumbai | D2: 5 | E2: 3 | F2: 1032.29 | G2: 2132.95 | H2: 213.3 | I2: 611.63 | J2: 1308.02
A3: 2 | B3: UK | C3: London | D3: 2 | E3: 1 | F3: 5316.57 | G3: 5316.57 | H3: 1329.14 | I3: 2240.25 | J3: 1747.18
A4: 3 | B4: Brazil | C4: Sao Paulo | D4: 6 | E4: 3 | F4: 827.81 | G4: 2241.32 | H4: 336.2 | I4: 1111.05 | J4: 794.07
A5: 4 | B5: Germany | C5: Munich | D5: 4 | E5: 1 | F5: 5139.02 | G5: 5139.02 | H5: 1798.66 | I5: 2922.76 | J5: 417.61
A6: 5 | B6: USA | C6: New York | D6: 4 | E6: 3 | F6: 4506.74 | G6: 9624.55 | H6: 2598.63 | I6: 2910.88 | J6: 4115.04
A7: 6 | B7: USA | C7: Chicago | D7: 5 | E7: 2 | F7: 4536.89 | G7: 7235.89 | H7: 1591.9 | I7: 2437.1 | J7: 3206.89
A8: 7 | B8: USA | C8: Chicago | D8: 7 | E8: 3 | F8: 3957.13 | G8: 8172.73 | H8: 2206.64 | I8: 4197.44 | J8: 1768.65
A9: 8 | B9: UK | C9: London | D9: 8 | E9: 2 | F9: 3568.25 | G9: 5214.34 | H9: 1303.58 | I9: 4948.41 | J9: -1037.65
A10: 9 | B10: Germany | C10: Berlin | D10: 2 | E10: 2 | F10: 5277.68 | G10: 7838.3 | H10: 2743.4 | I10: 2485.94 | J10: 2608.95
A11: 10 | B11: Brazil | C11: Sao Paulo | D11: 4 | E11: 3 | F11: 1256.63 | G11: 2425.63 | H11: 363.85 | I11: 902.75 | J11: 1159.04
A12: 11 | B12: USA | C12: Chicago | D12: 8 | E12: 3 | F12: 3240.5 | G12: 7497.82 | H12: 1649.52 | I12: 5856.22 | J12: -7.92
A13: 12 | B13: UK | C13: London | D13: 5 | E13: 3 | F13: 5768.09 | G13: 12306.86 | H13: 3692.06 | I13: 3665.66 | J13: 4949.14
... A5001: 5000 | B5001: Germany | C5001: Munich | D5001: 1 | E5001: 1 | F5001: 5021.42 | G5001: 5021.42 | H5001: 1757.5 | I5001: 1257.14 | J5001: 2006.78

Sheet PIVOT1 Country COMPARISION
A1: Country that has the highest saving rate-
A3: Country name | B3: Average of Total_Household_Income | C3: Average of Monthly_Expenses | D3: Average of Monthly_Savings | E3: Average of Savings Rate%
A4: USA | B4: 6682.4927 | C4: 2929.8024 | D4: 2109.4961 | E4: 0.32336205
A5: UK | B5: 7073.7997 | C5: 3067.5654 | D5: 2040.8497 | E5: 0.30718717
A6: India | B6: 1345.4775 | C6: 587.24528 | D6: 623.68461 | E6: 0.42077342
A7: Germany | B7: 7172.6152 | C7: 3275.9737 | D7: 1180.5755 | E7: 0.158798
A8: Brazil | B8: 2649.0738 | C8: 1157.7713 | D8: 1093.9416 | E8: 0.39788995
A9: Grand Total | B9: 4945.9231 | C9: 2189.3971 | D9: 1396.3328 | E9: 0.32178395

Sheet PIVOT-2 family Size Impact
A1: PIVOT 2 - Bigger family sizes experience lower savings and higher risk Flag-
A3: Row Labels | B3: Average of Monthly_Savings | C3: Average of Expence Ratio | D3: Count of Risk_Flag
A4: 1 | B4: 1150.314 | C4: 0.54068853 | D4: 645
A5: 2 | B5: 1499.2859 | C5: 0.58332116 | D5: 607
A6: 3 | B6: 1741.8436 | C6: 0.59180169 | D6: 614
A7: 4 | B7: 1533.9912 | C7: 0.67138939 | D7: 619
A8: 5 | B8: 1610.3058 | C8: 0.7009449 | D8: 660
A9: 6 | B9: 1409.4629 | C9: 0.72948085 | D9: 589
A10: 7 | B10: 1166.3825 | C10: 0.78151628 | D10: 621
A11: 8 | B11: 1067.2516 | C11: 0.82781254 | D11: 630
A12: Grand Total | B12: 1396.3328 | C12: 0.67821618 | D12: 4985

Sheet PIVOT-3 EARNER EFFECT
A1: PIVOT -3 Having 3 earners always beats having just 1 earner across different countries-
A3: Average of Savings Rate% | B3: Column Labels
A4: Row Labels | B4: Brazil | C4: Germany | D4: India | E4: UK | F4: USA | G4: Grand Total
A5: 1 | B5: 0.33514457 | C5: 0.095548517 | D5: 0.33755353 | E5: 0.20581505 | F5: 0.22411035 | G5: 0.23887597
A6: 2 | B6: 0.42985588 | C6: 0.20393179 | D6: 0.4335003 | E6: 0.31769306 | F6: 0.39342218 | G6: 0.3601618
A7: 3 | B7: 0.43011473 | C7: 0.18542399 | D7: 0.47768814 | E7: 0.38234889 | F7: 0.36246277 | G7: 0.36609501
A8: Grand Total | B8: 0.39788995 | C8: 0.158798 | D8: 0.42077342 | E8: 0.30718717 | F8: 0.32336205 | G8: 0.32178395

Sheet Step7 Scenario Model
A1: Expense Reduction % | B1: House Hold Becoming safe
A2: 0.05 | B2: =COUNTIFS('STEP-2 CLEANED_DATA_ FROM_POWER'!$N:$N,"High Risk",'STEP-2 CLEANED_DATA_ FROM_POWER'!$S:$S,">0") -> 98
A3: 0.1 | B3: =COUNTIFS('STEP-2 CLEANED_DATA_ FROM_POWER'!$N:$N,"High Risk",'STEP-2 CLEANED_DATA_ FROM_POWER'!$T:$T,">0") -> 320
A4: 0.15 | B4: =COUNTIFS('STEP-2 CLEANED_DATA_ FROM_POWER'!$N:$N,"High Risk",'STEP-2 CLEANED_DATA_ FROM_POWER'!$U:$U,">0") -> 498
A5: 0.2 | B5: =COUNTIFS('STEP-2 CLEANED_DATA_ FROM_POWER'!$N:$N,"High Risk",'STEP-2 CLEANED_DATA_ FROM_POWER'!$V:$V,">0") -> 700
